{
    "code": 200,
    "status": true,
    "msg": "",
    "time": "2024-02-07 08:19:19",
    "param_obj": {
        "dept_name": "ด่านขุนทด",
        "offset": 0,
        "limit": 20
    },
    "summary": {
        "total": 7
    },
    "result": [
        {
            "dept_code": "5300801",
            "dept_name": "เทศบาลตำบลด่านขุนทด"
        },
        {
            "dept_code": "001087700",
            "dept_name": "โรงพยาบาลด่านขุนทด"
        },
        {
            "dept_code": "1030050010",
            "dept_name": "โรงเรียนด่านขุนทด"
        },
        {
            "dept_code": "1030052001",
            "dept_name": "โรงเรียนมัธยมด่านขุนทด"
        },
        {
            "dept_code": "1230080000",
            "dept_name": "ศูนย์ กศน.อำเภอด่านขุนทด"
        },
        {
            "dept_code": "E15090136",
            "dept_name": "ศูนย์พัฒนาเด็กเล็กเทศบาลตำบลด่านขุนทด"
        },
        {
            "dept_code": "6300802",
            "dept_name": "องค์การบริหารส่วนตำบลด่านขุนทด"
        }
    ]
}